nti.contentfragments-1.9.0-py3.7-nspkg.pth
nti/contentfragments/__init__.py
nti/contentfragments/censor.py
nti/contentfragments/configure.zcml
nti/contentfragments/html.py
nti/contentfragments/interfaces.py
nti/contentfragments/latex.py
nti/contentfragments/mime.types
nti/contentfragments/profanity_list.txt
nti/contentfragments/prohibited_words.txt
nti/contentfragments/punctuation.py
nti/contentfragments/rst.py
nti/contentfragments/schema.py
nti/contentfragments/types.csv
nti/contentfragments/urlmatcher.py
nti/contentfragments/white_list.txt
nti/contentfragments/tests/__init__.py
nti/contentfragments/tests/contenttypes-notes-sanitized.txt
nti/contentfragments/tests/contenttypes-notes-tosanitize.plist
nti/contentfragments/tests/test_censor.py
nti/contentfragments/tests/test_html.py
nti/contentfragments/tests/test_interfaces.py
nti/contentfragments/tests/test_latex.py
nti/contentfragments/tests/test_rst.py
nti/contentfragments/tests/test_schema.py
nti/contentfragments/tests/test_urlmatcher.py
nti.contentfragments-1.9.0.dist-info/LICENSE
nti.contentfragments-1.9.0.dist-info/METADATA
nti.contentfragments-1.9.0.dist-info/WHEEL
nti.contentfragments-1.9.0.dist-info/entry_points.txt
nti.contentfragments-1.9.0.dist-info/namespace_packages.txt
nti.contentfragments-1.9.0.dist-info/top_level.txt
nti.contentfragments-1.9.0.dist-info/zip-safe
nti.contentfragments-1.9.0.dist-info/RECORD
