Metadata-Version: 2.1
Name: nti.contentfragments
Version: 1.9.0
Summary: NTI ContentFragments
Home-page: https://github.com/NextThought/nti.contentfragments
Author: Jason Madden
Author-email: jason@nextthought.com
License: Apache
Keywords: Content fragments semantic typing interfaces classes sanitize censor
Platform: UNKNOWN
Classifier: Intended Audience :: Developers
Classifier: Natural Language :: English
Classifier: Operating System :: OS Independent
Classifier: Programming Language :: Python :: 2
Classifier: Programming Language :: Python :: 2.7
Classifier: Programming Language :: Python :: 3
Classifier: Programming Language :: Python :: 3.6
Classifier: Programming Language :: Python :: 3.7
Classifier: Programming Language :: Python :: 3.8
Classifier: Programming Language :: Python :: 3.9
Classifier: Programming Language :: Python :: 3.10
Classifier: Programming Language :: Python :: Implementation :: CPython
Classifier: Programming Language :: Python :: Implementation :: PyPy
License-File: LICENSE
Requires-Dist: setuptools
Requires-Dist: html5lib
Requires-Dist: lxml (>=4.2.5)
Requires-Dist: repoze.lru (>=0.6)
Requires-Dist: zope.component (>=4.6.1)
Requires-Dist: zope.event (>=4.4.0)
Requires-Dist: zope.interface (>=5.0.0)
Requires-Dist: zope.mimetype (>=2.4.0)
Requires-Dist: zope.security (>=5.1.1)
Requires-Dist: zope.cachedescriptors (>=4.3.1)
Requires-Dist: nti.schema (>=1.14.0)
Requires-Dist: docutils
Requires-Dist: html2text (>=2019.8.11)
Requires-Dist: datrie (>=0.8.2); platform_python_implementation == "CPython"
Provides-Extra: docs
Requires-Dist: repoze.sphinx.autointerface; extra == 'docs'
Requires-Dist: sphinx-rtd-theme; extra == 'docs'
Provides-Extra: test
Requires-Dist: pyhamcrest; extra == 'test'
Requires-Dist: zope.testing; extra == 'test'
Requires-Dist: nti.testing; extra == 'test'
Requires-Dist: zope.testrunner; extra == 'test'
